Workbook
Name Slicer_Age: #N/A
Name Slicer_Age1: #N/A
Name Slicer_Gender: #N/A
Name Slicer_Gender1: #N/A

Sheet Finance_data
A1: =PROPER("gender") -> Gender | B1: Age | C1: Investment_Avenues | D1: Mutual_Funds | E1: Equity_Market | F1: Debentures | G1: Government_Bonds | H1: Fixed_Deposits | I1: PPF | J1: Gold | K1: Stock_Marktet | L1: Factor | M1: Objective | N1: Purpose | O1: Duration | P1: Invest_Monitor | Q1: Expect | R1: Avenue | S1: What are your savings objectives? | T1: Reason_Equity | U1: Reason_Mutual | V1: Reason_Bonds | W1: Reason_FD | X1: Source | Y1: Age Group | Z1: Low Risk investir | AA1: AVG Return Value | AB1: High RISK | AC1: Low Risk | AD1: Risk Study | AE1: Investor Persona | AF1: Auto Ditect
A2: Female | B2: 34 | C2: Yes | D2: 1 | E2: 2 | F2: 5 | G2: 3 | H2: 7 | I2: 6 | J2: 4 | K2: Yes | L2: Returns | M2: Capital Appreciation | N2: Wealth Creation | O2: 1-3 years | P2: Monthly | Q2: 20%-30% | R2: Mutual Fund | S2: Retirement Plan | T2: Capital Appreciation | U2: Better Returns | V2: Safe Investment | W2: Fixed Returns | X2: Newspapers and Magazines | Y2: {=_xlfn.IFS(B2<=30,"20-30",B2<=40,"30-40")} -> 30-40 | Z2: =IF(OR(G2>5,H2>5,I2>5),"yes","no") -> yes | AA2: =IF(Q2="10%-20%",15,IF(Q2="20%-30%",25,35)) -> 25 | AB2: =D2+E2+F2 -> 8 | AC2: =G2+H2+J2 -> 14 | AD2: =IF(AB2>AC2,"High risk","Low Risk") -> Low Risk | AE2: =IF(OR(B2<=25,AD2="High "),"Young Aggressive",IF(OR(B2<=35,AD2="Low"),"Conservative")) -> Conservative | AF2: =IF(AD2="High Risk","Equity/Mutual Funds", "FD/Bonds/PPF") -> FD/Bonds/PPF
A3: Female | B3: 23 | C3: Yes | D3: 4 | E3: 3 | F3: 2 | G3: 1 | H3: 5 | I3: 6 | J3: 7 | K3: No | L3: Locking Period | M3: Capital Appreciation | N3: Wealth Creation | O3: More than 5 years | P3: Weekly | Q3: 20%-30% | R3: Mutual Fund | S3: Health Care | T3: Dividend | U3: Better Returns | V3: Safe Investment | W3: High Interest Rates | X3: Financial Consultants | Y3: {=_xlfn.IFS(B3<=30,"20-30",B3<=40,"30-40")} -> 20-30 | Z3: =IF(OR(G3>5,H3>5,I3>5),"yes","no") -> yes | AA3: =IF(Q3="10%-20%",15,IF(Q3="20%-30%",25,35)) -> 25 | AB3: =D3+E3+F3 -> 9 | AC3: =G3+H3+J3 -> 13 | AD3: =IF(AB3>AC3,"High risk","Low Risk") -> Low Risk | AE3: =IF(OR(B3<=25,AD3="High "),"Young Aggressive",IF(OR(B3<=35,AD3="Low"),"Conservative")) -> Young Aggressive | AF3: =IF(AD3="High Risk","Equity/Mutual Funds", "FD/Bonds/PPF") -> FD/Bonds/PPF
A4: Male | B4: 30 | C4: Yes | D4: 3 | E4: 6 | F4: 4 | G4: 2 | H4: 5 | I4: 1 | J4: 7 | K4: Yes | L4: Returns | M4: Capital Appreciation | N4: Wealth Creation | O4: 3-5 years | P4: Daily | Q4: 20%-30% | R4: Equity | S4: Retirement Plan | T4: Capital Appreciation | U4: Tax Benefits | V4: Assured Returns | W4: Fixed Returns | X4: Television | Y4: {=_xlfn.IFS(B4<=30,"20-30",B4<=40,"30-40")} -> 20-30 | Z4: =IF(OR(G4>5,H4>5,I4>5),"yes","no") -> no | AA4: =IF(Q4="10%-20%",15,IF(Q4="20%-30%",25,35)) -> 25 | AB4: =D4+E4+F4 -> 13 | AC4: =G4+H4+J4 -> 14 | AD4: =IF(AB4>AC4,"High risk","Low Risk") -> Low Risk | AE4: =IF(OR(B4<=25,AD4="High "),"Young Aggressive",IF(OR(B4<=35,AD4="Low"),"Conservative")) -> Conservative | AF4: =IF(AD4="High Risk","Equity/Mutual Funds", "FD/Bonds/PPF") -> FD/Bonds/PPF
A5: Male | B5: 22 | C5: Yes | D5: 2 | E5: 1 | F5: 3 | G5: 7 | H5: 6 | I5: 4 | J5: 5 | K5: Yes | L5: Returns | M5: Income | N5: Wealth Creation | O5: Less than 1 year | P5: Daily | Q5: 10%-20% | R5: Equity | S5: Retirement Plan | T5: Dividend | U5: Fund Diversification | V5: Tax Incentives | W5: High Interest Rates | X5: Internet | Y5: {=_xlfn.IFS(B5<=30,"20-30",B5<=40,"30-40")} -> 20-30 | Z5: =IF(OR(G5>5,H5>5,I5>5),"yes","no") -> yes | AA5: =IF(Q5="10%-20%",15,IF(Q5="20%-30%",25,35)) -> 15 | AB5: =D5+E5+F5 -> 6 | AC5: =G5+H5+J5 -> 18 | AD5: =IF(AB5>AC5,"High risk","Low Risk") -> Low Risk | AE5: =IF(OR(B5<=25,AD5="High "),"Young Aggressive",IF(OR(B5<=35,AD5="Low"),"Conservative")) -> Young Aggressive | AF5: =IF(AD5="High Risk","Equity/Mutual Funds", "FD/Bonds/PPF") -> FD/Bonds/PPF
A6: Female | B6: 24 | C6: No | D6: 2 | E6: 1 | F6: 3 | G6: 6 | H6: 4 | I6: 5 | J6: 7 | K6: No | L6: Returns | M6: Income | N6: Wealth Creation | O6: Less than 1 year | P6: Daily | Q6: 20%-30% | R6: Equity | S6: Retirement Plan | T6: Capital Appreciation | U6: Better Returns | V6: Safe Investment | W6: Risk Free | X6: Internet | Y6: {=_xlfn.IFS(B6<=30,"20-30",B6<=40,"30-40")} -> 20-30 | Z6: =IF(OR(G6>5,H6>5,I6>5),"yes","no") -> yes | AA6: =IF(Q6="10%-20%",15,IF(Q6="20%-30%",25,35)) -> 25 | AB6: =D6+E6+F6 -> 6 | AC6: =G6+H6+J6 -> 17 | AD6: =IF(AB6>AC6,"High risk","Low Risk") -> Low Risk | AE6: =IF(OR(B6<=25,AD6="High "),"Young Aggressive",IF(OR(B6<=35,AD6="Low"),"Conservative")) -> Young Aggressive | AF6: =IF(AD6="High Risk","Equity/Mutual Funds", "FD/Bonds/PPF") -> FD/Bonds/PPF
A7: Female | B7: 24 | C7: No | D7: 7 | E7: 5 | F7: 4 | G7: 6 | H7: 3 | I7: 1 | J7: 2 | K7: No | L7: Risk | M7: Capital Appreciation | N7: Wealth Creation | O7: 1-3 years | P7: Daily | Q7: 30%-40% | R7: Mutual Fund | S7: Retirement Plan | T7: Liquidity | U7: Fund Diversification | V7: Safe Investment | W7: Risk Free | X7: Internet | Y7: {=_xlfn.IFS(B7<=30,"20-30",B7<=40,"30-40")} -> 20-30 | Z7: =IF(OR(G7>5,H7>5,I7>5),"yes","no") -> yes | AA7: =IF(Q7="10%-20%",15,IF(Q7="20%-30%",25,35)) -> 35 | AB7: =D7+E7+F7 -> 16 | AC7: =G7+H7+J7 -> 11 | AD7: =IF(AB7>AC7,"High risk","Low Risk") -> High risk | AE7: =IF(OR(B7<=25,AD7="High "),"Young Aggressive",IF(OR(B7<=35,AD7="Low"),"Conservative")) -> Young Aggressive | AF7: =IF(AD7="High Risk","Equity/Mutual Funds", "FD/Bonds/PPF") -> Equity/Mutual Funds
A8: Female | B8: 27 | C8: Yes | D8: 3 | E8: 6 | F8: 4 | G8: 2 | H8: 5 | I8: 1 | J8: 7 | K8: Yes | L8: Returns | M8: Capital Appreciation | N8: Wealth Creation | O8: 3-5 years | P8: Monthly | Q8: 20%-30% | R8: Equity | S8: Retirement Plan | T8: Capital Appreciation | U8: Better Returns | V8: Assured Returns | W8: High Interest Rates | X8: Financial Consultants | Y8: {=_xlfn.IFS(B8<=30,"20-30",B8<=40,"30-40")} -> 20-30 | Z8: =IF(OR(G8>5,H8>5,I8>5),"yes","no") -> no | AA8: =IF(Q8="10%-20%",15,IF(Q8="20%-30%",25,35)) -> 25 | AB8: =D8+E8+F8 -> 13 | AC8: =G8+H8+J8 -> 14 | AD8: =IF(AB8>AC8,"High risk","Low Risk") -> Low Risk | AE8: =IF(OR(B8<=25,AD8="High "),"Young Aggressive",IF(OR(B8<=35,AD8="Low"),"Conservative")) -> Conservative | AF8: =IF(AD8="High Risk","Equity/Mutual Funds", "FD/Bonds/PPF") -> FD/Bonds/PPF
A9: Male | B9: 21 | C9: Yes | D9: 2 | E9: 3 | F9: 7 | G9: 4 | H9: 6 | I9: 1 | J9: 5 | K9: Yes | L9: Risk | M9: Capital Appreciation | N9: Wealth Creation | O9: 3-5 years | P9: Monthly | Q9: 20%-30% | R9: Mutual Fund | S9: Retirement Plan | T9: Capital Appreciation | U9: Better Returns | V9: Assured Returns | W9: Risk Free | X9: Newspapers and Magazines | Y9: {=_xlfn.IFS(B9<=30,"20-30",B9<=40,"30-40")} -> 20-30 | Z9: =IF(OR(G9>5,H9>5,I9>5),"yes","no") -> yes | AA9: =IF(Q9="10%-20%",15,IF(Q9="20%-30%",25,35)) -> 25 | AB9: =D9+E9+F9 -> 12 | AC9: =G9+H9+J9 -> 15 | AD9: =IF(AB9>AC9,"High risk","Low Risk") -> Low Risk | AE9: =IF(OR(B9<=25,AD9="High "),"Young Aggressive",IF(OR(B9<=35,AD9="Low"),"Conservative")) -> Young Aggressive | AF9: =IF(AD9="High Risk","Equity/Mutual Funds", "FD/Bonds/PPF") -> FD/Bonds/PPF
A10: Male | B10: 35 | C10: Yes | D10: 2 | E10: 4 | F10: 7 | G10: 5 | H10: 3 | I10: 1 | J10: 6 | K10: Yes | L10: Returns | M10: Growth | N10: Savings for Future | O10: 1-3 years | P10: Weekly | Q10: 20%-30% | R10: Equity | S10: Retirement Plan | T10: Capital Appreciation | U10: Fund Diversification | V10: Safe Investment | W10: Fixed Returns | X10: Television | Y10: {=_xlfn.IFS(B10<=30,"20-30",B10<=40,"30-40")} -> 30-40 | Z10: =IF(OR(G10>5,H10>5,I10>5),"yes","no") -> no | AA10: =IF(Q10="10%-20%",15,IF(Q10="20%-30%",25,35)) -> 25 | AB10: =D10+E10+F10 -> 13 | AC10: =G10+H10+J10 -> 14 | AD10: =IF(AB10>AC10,"High risk","Low Risk") -> Low Risk | AE10: =IF(OR(B10<=25,AD10="High "),"Young Aggressive",IF(OR(B10<=35,AD10="Low"),"Conservative")) -> Conservative | AF10: =IF(AD10="High Risk","Equity/Mutual Funds", "FD/Bonds/PPF") -> FD/Bonds/PPF
A11: Male | B11: 31 | C11: Yes | D11: 1 | E11: 3 | F11: 7 | G11: 4 | H11: 5 | I11: 2 | J11: 6 | K11: Yes | L11: Returns | M11: Capital Appreciation | N11: Wealth Creation | O11: 3-5 years | P11: Monthly | Q11: 30%-40% | R11: Fixed Deposits | S11: Retirement Plan | T11: Capital Appreciation | U11: Fund Diversification | V11: Assured Returns | W11: Fixed Returns | X11: Newspapers and Magazines | Y11: {=_xlfn.IFS(B11<=30,"20-30",B11<=40,"30-40")} -> 30-40 | Z11: =IF(OR(G11>5,H11>5,I11>5),"yes","no") -> no | AA11: =IF(Q11="10%-20%",15,IF(Q11="20%-30%",25,35)) -> 35 | AB11: =D11+E11+F11 -> 11 | AC11: =G11+H11+J11 -> 15 | AD11: =IF(AB11>AC11,"High risk","Low Risk") -> Low Risk | AE11: =IF(OR(B11<=25,AD11="High "),"Young Aggressive",IF(OR(B11<=35,AD11="Low"),"Conservative")) -> Conservative | AF11: =IF(AD11="High Risk","Equity/Mutual Funds", "FD/Bonds/PPF") -> FD/Bonds/PPF
A12: Female | B12: 35 | C12: Yes | D12: 2 | E12: 4 | F12: 7 | G12: 5 | H12: 3 | I12: 1 | J12: 6 | K12: Yes | L12: Risk | M12: Growth | N12: Savings for Future | O12: 3-5 years | P12: Monthly | Q12: 20%-30% | R12: Mutual Fund | S12: Retirement Plan | T12: Capital Appreciation | U12: Better Returns | V12: Assured Returns | W12: Risk Free | X12: Financial Consultants | Y12: {=_xlfn.IFS(B12<=30,"20-30",B12<=40,"30-40")} -> 30-40 | Z12: =IF(OR(G12>5,H12>5,I12>5),"yes","no") -> no | AA12: =IF(Q12="10%-20%",15,IF(Q12="20%-30%",25,35)) -> 25 | AB12: =D12+E12+F12 -> 13 | AC12: =G12+H12+J12 -> 14 | AD12: =IF(AB12>AC12,"High risk","Low Risk") -> Low Risk | AE12: =IF(OR(B12<=25,AD12="High "),"Young Aggressive",IF(OR(B12<=35,AD12="Low"),"Conservative")) -> Conservative | AF12: =IF(AD12="High Risk","Equity/Mutual Funds", "FD/Bonds/PPF") -> FD/Bonds/PPF
A13: Male | B13: 29 | C13: Yes | D13: 2 | E13: 5 | F13: 7 | G13: 6 | H13: 3 | I13: 1 | J13: 4 | K13: Yes | L13: Risk | M13: Capital Appreciation | N13: Wealth Creation | O13: 1-3 years | P13: Monthly | Q13: 20%-30% | R13: Mutual Fund | S13: Retirement Plan | T13: Capital Appreciation | U13: Fund Diversification | V13: Assured Returns | W13: Fixed Returns | X13: Financial Consultants | Y13: {=_xlfn.IFS(B13<=30,"20-30",B13<=40,"30-40")} -> 20-30 | Z13: =IF(OR(G13>5,H13>5,I13>5),"yes","no") -> yes | AA13: =IF(Q13="10%-20%",15,IF(Q13="20%-30%",25,35)) -> 25 | AB13: =D13+E13+F13 -> 14 | AC13: =G13+H13+J13 -> 13 | AD13: =IF(AB13>AC13,"High risk","Low Risk") -> High risk | AE13: =IF(OR(B13<=25,AD13="High "),"Young Aggressive",IF(OR(B13<=35,AD13="Low"),"Conservative")) -> Conservative | AF13: =IF(AD13="High Risk","Equity/Mutual Funds", "FD/Bonds/PPF") -> Equity/Mutual Funds
... A41: Male | B41: 29 | C41: Yes | D41: 4 | E41: 3 | F41: 5 | G41: 7 | H41: 2 | I41: 1 | J41: 6 | K41: Yes | L41: Returns | M41: Capital Appreciation | N41: Wealth Creation | O41: 3-5 years | P41: Monthly | Q41: 20%-30% | R41: Fixed Deposits | S41: Retirement Plan | T41: Dividend | U41: Better Returns | V41: Safe Investment | W41: Fixed Returns | X41: Financial Consultants | Y41: {=_xlfn.IFS(B41<=30,"20-30",B41<=40,"30-40")} -> 20-30 | Z41: =IF(OR(G41>5,H41>5,I41>5),"yes","no") -> yes | AA41: =IF(Q41="10%-20%",15,IF(Q41="20%-30%",25,35)) -> 25 | AB41: =D41+E41+F41 -> 12 | AC41: =G41+H41+J41 -> 15 | AD41: =IF(AB41>AC41,"High risk","Low Risk") -> Low Risk | AE41: =IF(OR(B41<=25,AD41="High "),"Young Aggressive",IF(OR(B41<=35,AD41="Low"),"Conservative")) -> Conservative | AF41: =IF(AD41="High Risk","Equity/Mutual Funds", "FD/Bonds/PPF") -> FD/Bonds/PPF
D42: =SUM(D2:D41) -> 102 | E42: =SUM(E2:E41) -> 139 | F42: =SUM(F2:F41) -> 230 | G42: =SUM(G2:G41) -> 186 | H42: =SUM(H2:H41) -> 143 | I42: =SUM(I2:I41) -> 81 | J42: =SUM(J2:J41) -> 239

Sheet Basic
A1: Basic Investment Insights
A3: 7. Top 3 savings objectives. | B3: Value | D3: Metrics | E3: Value | G3: Count
A4: Education | B4: 3 | D4: 1. Total Investors | E4: =COUNTA(Finance_data!A2:A41) -> 40 | G4: 6. Gender VS Investment Avenues | H4: No | I4: Yes | J4: Grand Total
A5: Health Care | B5: 13 | G5: Female | H5: 3 | I5: 12 | J5: 15
A6: Retirement Plan | B6: 24 | D6: 2. Gender vise inv | G6: Male | I6: 25 | J6: 25
A7: Grand Total | B7: 40 | D7: Male | E7: =COUNTIF(Finance_data!A2:A41,"male") -> 25 | G7: Grand Total | H7: 3 | I7: 37 | J7: 40
D8: Female | E8: =COUNTIF(Finance_data!A2:A41,"Female") -> 15
D10: 3. Avg age of investors | E10: =AVERAGE(Finance_data!B2:B41) -> 27.8
D12: 4. Most prefered investment | E12: PPF
D14: 8. Chart of preference for Gold vs Equity.
D15: Gold | E15: =Finance_data!J42 -> 239
D16: Equity | E16: =Finance_data!E42 -> 139
D18: 9. % of investors monitor investments daily? | E18: =COUNTIF(Finance_data!P2:P41,"Daily")/100 -> 0.04 | G18: 5. COUNT of Values
G19: Count of Mutual_Funds | H19: 41
G20: Count of Equity_Market | H20: 41
G21: Count of Fixed_Deposits | H21: 41

Sheet Investment
A1: Investment Analysis
A3: Age Group | B3: Sum of Mutual_Funds | C3: Sum of Gold | D3: Sum of Fixed_Deposits | F3: Frequency of Checking | G3: Age Group | K3: Expected Retuns | L3: AVG Return Value..
A4: 25-30 | B4: 29 | C4: 56 | D4: 40 | F4: Duration | G4: 20-30 | H4: 30-40 | I4: Grand Total | K4: Equity | L4: 25
A5: 30-35 | B5: 53 | C5: 133 | D5: 67 | F5: Daily | G5: 4 | I5: 4 | K5: Fixed Deposits | L5: 26.111111
A6: Above 40 | B6: 20 | C6: 50 | D6: 36 | F6: Monthly | G6: 22 | H6: 7 | I6: 29 | K6: Mutual Fund | L6: 24.444444
A7: Grand Total | B7: 102 | C7: 239 | D7: 143 | F7: Weekly | G7: 5 | H7: 2 | I7: 7 | K7: Public Provident Fund | L7: 31.666667
F8: Grand Total | G8: 31 | H8: 9 | I8: 40 | K8: Grand Total | L8: 25.5
F10: Count of Investment_Avenues | G10: Column Labels
F11: Row Labels | G11: Female | H11: Male | I11: Grand Total
F12: No | G12: 3 | I12: 3
F13: Yes | G13: 12 | H13: 25 | I13: 37
F14: Grand Total | G14: 15 | H14: 25 | I14: 40
F16: Duration of Inv | G16: Count of Avenue
F17: 1-3 years | G17: 18
F18: 3-5 years | G18: 19
F19: Less than 1 year | G19: 2 | K19: Equity | L19: =Finance_data!E42 -> 139
F20: More than 5 years | G20: 1 | K20: Mutual Funds | L20: =Finance_data!D42 -> 102
F21: Grand Total | G21: 40 | K21: Low Risk Investors | L21: =COUNTIF(Finance_data!Z2:Z41,"yes")/COUNTA(Finance_data!Z2:Z41) -> 0.375

Sheet Strategic
A1: Strategic Investment Insights
A3: AVG Age | B3: Column Labels | L3: Investor | M3: Gender
A4: Row Labels | B4: Female | C4: Male | D4: (blank) | E4: Grand Total | L4: Personality | M4: Female | N4: Male | O4: Grand Total
A5: Education | B5: 21 | C5: 53 | E5: 74 | L5: Conservative | M5: 9 | N5: 21 | O5: 30
A6: Health Care | B6: 100 | C6: 249 | E6: 349 | L6: Hight risk | M6: 1 | N6: 3 | O6: 4
A7: Retirement Plan | B7: 295 | C7: 394 | E7: 689 | L7: Low Risk | M7: 8 | N7: 18 | O7: 26
A8: (blank) | L8: Young Aggressive | M8: 6 | N8: 4 | O8: 10
A9: Grand Total | B9: 416 | C9: 696 | E9: 1112 | L9: Hight risk | M9: 1 | N9: 1 | O9: 2
L10: Low Risk | M10: 5 | N10: 3 | O10: 8
G11: Risk Segment | H11: Gender | L11: Grand Total | M11: 15 | N11: 25 | O11: 40
G12: Risk Levels | H12: Female | I12: Male | J12: Grand Total
G13: Hight risk | H13: 2 | I13: 4 | J13: 6 | L13: Risk Detection | M13: Risk Level
G14: Low Risk | H14: 13 | I14: 21 | J14: 34 | L14: Investment Options | M14: High risk | N14: Low Risk | O14: Grand Total
G15: Grand Total | H15: 15 | I15: 25 | J15: 40 | L15: Equity/Mutual Funds | M15: 6 | O15: 6
L16: FD/Bonds/PPF | N16: 34 | O16: 34
L17: Grand Total | M17: 6 | N17: 34 | O17: 40

Sheet Insights
A1: Insights
A3: Basic Insights
A5: The dataset contains a diverse group of investors with varying preferences.
A6: A majority of investors actively monitor their investments.
A7: Mutual Funds and Equity are among the most preferred investment avenues.
A8: Gold and Fixed Deposits are chosen as safer investment options.
A12: Gender-Based Insights
A14: Male investors show higher inclination towards Equity and Mutual Funds.
A15: Female investors prefer relatively safer options like FD and Gold.
A16: Overall participation is balanced across genders.
M17: learn coac x .live
A20: Age-Based Insights
A22: Younger investors (<30) prefer high-risk investments like Equity.
A23: Middle-aged investors (30–40) prefer Mutual Funds (balanced approach).
A24: Older investors prefer low-risk options like FD, Bonds, and PPF.
A28: Investment Preference Insights
A30: Equity provides the highest expected returns among all avenues.
A31: Fixed Deposits and Bonds provide stable but lower returns.
A32: Investors diversify their portfolio across multiple options.
A36: Objective vs Investment Insights
A38: Investors with wealth creation goals prefer Equity and Mutual Funds.
A39: Investors focused on safety prefer FD, PPF, and Bonds.
A40: There is a clear alignment between objectives and investment choices.
... A76: Age, objective, and risk appetite strongly influence investment decisions.
